{"data":{"markdownRemark":{"frontmatter":{"title":"Education","subtitle":"My Qualification"}},"allMarkdownRemark":{"edges":[{"node":{"id":"ea85f09c-ad43-5e17-b10b-3c1723a00641","html":"<p>Lorem ipsum dolor sit amet, consectetur adipiscing elit, sed do eiusmod tempor incididunt ut labore et dolore magna aliqua. Ut enim ad minim veniam, quis nostrud exercitation ullamco laborist.</p>","frontmatter":{"university":"Stanford University","degree":"Master of Science","startDate":"Oct 2008","endDate":"Jul 2010"}}},{"node":{"id":"bdeadebd-22db-51e8-b5d9-1838671d8850","html":"<p>Lorem ipsum dolor sit amet, consectetur adipiscing elit, sed do eiusmod tempor incididunt ut labore et dolore magna aliqua. Lorem ipsum dolor sit amet, consectetur adipiscing elit.</p>","frontmatter":{"university":"Columbia University","degree":"Bachelor","startDate":"Oct 2005","endDate":"Jul 2008"}}}]}}}